pixivpy_async/__init__.py
pixivpy_async/aapi.py
pixivpy_async/api.py
pixivpy_async/bapi.py
pixivpy_async/bypass_sni.py
pixivpy_async/client.py
pixivpy_async/error.py
pixivpy_async/net.py
pixivpy_async/papi.py
pixivpy_async/retry.py
pixivpy_async/sync.py
pixivpy_async/utils.py
PixivPy_Async-1.2.14.dist-info/LICENSE
PixivPy_Async-1.2.14.dist-info/METADATA
PixivPy_Async-1.2.14.dist-info/WHEEL
PixivPy_Async-1.2.14.dist-info/top_level.txt
PixivPy_Async-1.2.14.dist-info/RECORD
