Metadata-Version: 2.1
Name: PixivPy-Async
Version: 1.2.14
Summary: Pure Python 3 Async Pixiv API
Home-page: https://github.com/Mikubill/pixivpy-async
Author: Mikubill
License: UNKNOWN
Keywords: pixiv,api,pixivpy,pixivpy_async
Platform: UNKNOWN
Classifier: Operating System :: OS Independent
Classifier: Programming Language :: Python :: 3
Requires-Python: >=3.5.3
License-File: LICENSE
